nestdi-0.2.0.dist-info/METADATA
nestdi-0.2.0.dist-info/WHEEL
nestdi-0.2.0.dist-info/entry_points.txt
nestdi/__init__.py
nestdi/py.typed
nestdi-0.2.0.dist-info/RECORD
