Metadata-Version: 2.1
Name: nestdi
Version: 0.2.0
Summary: Default template for PDM package
Author-Email: victorgabrieldeon <victordeonroyale@gmail.com>
License: MIT
Requires-Python: >=3.12
